[{"externalId": "1716", "firstName": "", "lastName": "", "teamExternalId": "1610612766", "position": "G", "jersey": "0", "height": "6-5", "weight": "185", "birthDate": "JAN 23, 1979", "age": 31.0}, {"externalId": "1536", "firstName": "", "lastName": "", "teamExternalId": "1610612766", "position": "G-F", "jersey": "1", "height": "6-8", "weight": "215", "birthDate": "APR 05, 1978", "age": 32.0}, {"externalId": "2222", "firstName": "", "lastName": "", "teamExternalId": "1610612766", "position": "F", "jersey": "3", "height": "6-7", "weight": "220", "birthDate": "JUL 23, 1982", "age": 27.0}, {"externalId": "201974", "firstName": "", "lastName": "", "teamExternalId": "1610612766", "position": "F", "jersey": "4", "height": "6-8", "weight": "227", "birthDate": "SEP 08, 1987", "age": 22.0}, {"externalId": "2199", "firstName": "", "lastName": "", "teamExternalId": "1610612766", "position": "C", "jersey": "6", "height": "7-1", "weight": "235", "birthDate": "OCT 02, 1982", "age": 27.0}, {"externalId": "2205", "firstName": "", "lastName": "", "teamExternalId": "1610612766", "position": "C", "jersey": "7", "height": "7-0", "weight": "280", "birthDate": "JAN 30, 1982", "age": 28.0}, {"externalId": "200748", "firstName": "", "lastName": "", "teamExternalId": "1610612766", "position": "F", "jersey": "12", "height": "6-10", "weight": "225", "birthDate": "AUG 17, 1986", "age": 23.0}, {"externalId": "1737", "firstName": "", "lastName": "", "teamExternalId": "1610612766", "position": "C", "jersey": "13", "height": "6-10", "weight": "250", "birthDate": "SEP 05, 1977", "age": 32.0}, {"externalId": "201571", "firstName": "", "lastName": "", "teamExternalId": "1610612766", "position": "G", "jersey": "14", "height": "6-0", "weight": "180", "birthDate": "NOV 10, 1987", "age": 22.0}, {"externalId": "201945", "firstName": "", "lastName": "", "teamExternalId": "1610612766", "position": "G", "jersey": "15", "height": "6-5", "weight": "215", "birthDate": "DEC 09, 1987", "age": 22.0}, {"externalId": "101109", "firstName": "", "lastName": "", "teamExternalId": "1610612766", "position": "G", "jersey": "20", "height": "6-1", "weight": "198", "birthDate": "JUN 26, 1984", "age": 26.0}, {"externalId": "201582", "firstName": "", "lastName": "", "teamExternalId": "1610612766", "position": "C", "jersey": "21", "height": "7-0", "weight": "220", "birthDate": "MAY 06, 1988", "age": 22.0}, {"externalId": "101211", "firstName": "", "lastName": "", "teamExternalId": "1610612766", "position": "G-F", "jersey": "23", "height": "6-6", "weight": "215", "birthDate": "JUN 11, 1982", "age": 28.0}, {"externalId": "2564", "firstName": "", "lastName": "", "teamExternalId": "1610612766", "position": "F", "jersey": "32", "height": "6-8", "weight": "235", "birthDate": "APR 16, 1982", "age": 28.0}, {"externalId": "689", "firstName": "", "lastName": "", "teamExternalId": "1610612766", "position": "C", "jersey": "42", "height": "6-10", "weight": "235", "birthDate": "APR 17, 1973", "age": 37.0}]