[{"externalId": "200751", "firstName": "Randy", "lastName": "Foye", "teamExternalId": "1610612751", "position": "G", "jersey": "2", "height": "6-4", "weight": "218", "birthDate": "SEP 24, 1983", "age": 33, "college": "Villanova"}, {"externalId": "203930", "firstName": "Sean", "lastName": "Kilpatrick", "teamExternalId": "1610612751", "position": "G", "jersey": "6", "height": "6-4", "weight": "219", "birthDate": "JAN 06, 1990", "age": 27, "college": "Cincinnati"}, {"externalId": "202391", "firstName": "Jeremy", "lastName": "Lin", "teamExternalId": "1610612751", "position": "G", "jersey": "7", "height": "6-3", "weight": "200", "birthDate": "AUG 23, 1988", "age": 28, "college": "Harvard"}, {"externalId": "203915", "firstName": "Spencer", "lastName": "Dinwiddie", "teamExternalId": "1610612751", "position": "G", "jersey": "8", "height": "6-6", "weight": "200", "birthDate": "APR 06, 1993", "age": 24, "college": "Colorado"}, {"externalId": "203462", "firstName": "Archie", "lastName": "Goodwin", "teamExternalId": "1610612751", "position": "G", "jersey": "10", "height": "6-5", "weight": "205", "birthDate": "AUG 17, 1994", "age": 22, "college": "Kentucky"}, {"externalId": "201572", "firstName": "Brook", "lastName": "Lopez", "teamExternalId": "1610612751", "position": "C", "jersey": "11", "height": "7-0", "weight": "268", "birthDate": "APR 01, 1988", "age": 29, "college": "Stanford"}, {"externalId": "203925", "firstName": "Joe", "lastName": "Harris", "teamExternalId": "1610612751", "position": "F-G", "jersey": "12", "height": "6-6", "weight": "219", "birthDate": "SEP 06, 1991", "age": 25, "college": "Virginia"}, {"externalId": "203112", "firstName": "Quincy", "lastName": "Acy", "teamExternalId": "1610612751", "position": "F", "jersey": "13", "height": "6-7", "weight": "240", "birthDate": "OCT 06, 1990", "age": 26, "college": "Baylor"}, {"externalId": "203909", "firstName": "KJ", "lastName": "McDaniels", "teamExternalId": "1610612751", "position": "G-F", "jersey": "14", "height": "6-6", "weight": "205", "birthDate": "FEB 09, 1993", "age": 24, "college": "Clemson"}, {"externalId": "1627785", "firstName": "Isaiah", "lastName": "Whitehead", "teamExternalId": "1610612751", "position": "G", "jersey": "15", "height": "6-4", "weight": "213", "birthDate": "MAR 08, 1995", "age": 22, "college": "Seton Hall"}, {"externalId": "1627747", "firstName": "Caris", "lastName": "LeVert", "teamExternalId": "1610612751", "position": "G-F", "jersey": "22", "height": "6-7", "weight": "203", "birthDate": "AUG 25, 1994", "age": 22, "college": "Michigan"}, {"externalId": "1626178", "firstName": "Rondae", "lastName": "Hollis-Jefferson", "teamExternalId": "1610612751", "position": "F", "jersey": "24", "height": "6-7", "weight": "214", "birthDate": "JAN 03, 1995", "age": 22, "college": "Arizona"}, {"externalId": "202344", "firstName": "Trevor", "lastName": "Booker", "teamExternalId": "1610612751", "position": "F", "jersey": "35", "height": "6-8", "weight": "228", "birthDate": "NOV 25, 1987", "age": 29, "college": "Clemson"}, {"externalId": "203120", "firstName": "Justin", "lastName": "Hamilton", "teamExternalId": "1610612751", "position": "C", "jersey": "41", "height": "7-0", "weight": "255", "birthDate": "APR 01, 1990", "age": 27, "college": "Louisiana State"}, {"externalId": "203094", "firstName": "Andrew", "lastName": "Nicholson", "teamExternalId": "1610612751", "position": "F", "jersey": "44", "height": "6-9", "weight": "250", "birthDate": "DEC 08, 1989", "age": 27, "college": "St. Bonaventure"}]