[{"externalId": "2405", "firstName": "", "lastName": "", "teamExternalId": "1610612752", "position": "F-C", "jersey": "1", "height": "6-10", "weight": "240", "birthDate": "NOV 16, 1982", "age": 28.0}, {"externalId": "201974", "firstName": "", "lastName": "", "teamExternalId": "1610612752", "position": "F", "jersey": "2", "height": "6-8", "weight": "220", "birthDate": "SEP 08, 1987", "age": 23.0}, {"externalId": "200761", "firstName": "", "lastName": "", "teamExternalId": "1610612752", "position": "F", "jersey": "3", "height": "6-9", "weight": "230", "birthDate": "FEB 16, 1986", "age": 25.0}, {"externalId": "1497", "firstName": "", "lastName": "", "teamExternalId": "1610612752", "position": "G", "jersey": "4", "height": "6-3", "weight": "210", "birthDate": "SEP 25, 1976", "age": 34.0}, {"externalId": "201611", "firstName": "", "lastName": "", "teamExternalId": "1610612752", "position": "G-F", "jersey": "5", "height": "6-6", "weight": "220", "birthDate": "OCT 09, 1987", "age": 23.0}, {"externalId": "202361", "firstName": "", "lastName": "", "teamExternalId": "1610612752", "position": "G", "jersey": "6", "height": "6-7", "weight": "210", "birthDate": "JUN 27, 1988", "age": 23.0}, {"externalId": "2546", "firstName": "", "lastName": "", "teamExternalId": "1610612752", "position": "F", "jersey": "7", "height": "6-8", "weight": "230", "birthDate": "MAY 29, 1984", "age": 27.0}, {"externalId": "2407", "firstName": "", "lastName": "", "teamExternalId": "1610612752", "position": "F", "jersey": "9", "height": "6-11", "weight": "240", "birthDate": "NOV 25, 1981", "age": 29.0}, {"externalId": "202360", "firstName": "", "lastName": "", "teamExternalId": "1610612752", "position": "G", "jersey": "11", "height": "6-4", "weight": "190", "birthDate": "NOV 02, 1986", "age": 24.0}, {"externalId": "200749", "firstName": "", "lastName": "", "teamExternalId": "1610612752", "position": "F", "jersey": "13", "height": "6-9", "weight": "250", "birthDate": "OCT 21, 1983", "age": 27.0}, {"externalId": "101142", "firstName": "", "lastName": "", "teamExternalId": "1610612752", "position": "C", "jersey": "14", "height": "6-10", "weight": "245", "birthDate": "JAN 13, 1983", "age": 28.0}, {"externalId": "2427", "firstName": "", "lastName": "", "teamExternalId": "1610612752", "position": "G", "jersey": "18", "height": "6-5", "weight": "205", "birthDate": "SEP 10, 1980", "age": 30.0}, {"externalId": "201962", "firstName": "", "lastName": "", "teamExternalId": "1610612752", "position": "G", "jersey": "23", "height": "6-2", "weight": "185", "birthDate": "MAR 16, 1986", "age": 25.0}, {"externalId": "1853", "firstName": "", "lastName": "", "teamExternalId": "1610612752", "position": "G", "jersey": "25", "height": "6-2", "weight": "195", "birthDate": "JUN 16, 1975", "age": 36.0}, {"externalId": "200764", "firstName": "", "lastName": "", "teamExternalId": "1610612752", "position": "F", "jersey": "32", "height": "6-8", "weight": "208", "birthDate": "JUL 14, 1984", "age": 26.0}]